{"name":"bdaddedfabaaacf","url":"index.html (等资源+1)","showName":"picture","appid":"com.xiaxia.myapp","icon":"","iconPath":"C:\\Users\\ThtScorpion\\AppData\\Roaming\\com.pakeplus.pacbao\\cfeth70wsi.png","iconRound":true,"state":true,"single":true,"injectJq":true,"tauriApi":false,"devbug":false,"version":"0.0.2","preview":"desktop","platform":["1-1","1-2"],"width":800,"height":600,"desc":"","jsFile":[],"filterCss":"","customJs":"<!DOCTYPE html>\n<html lang=\"en\">\n<head>\n    <meta charset=\"UTF-8\">\n    <meta name=\"viewport\" content=\"width=device-width, initial-scale=1.0\">\n    <title>图片墙 · 编辑模式无高亮 + 固定初始图</title>\n    <style>\n        * {\n            box-sizing: border-box;\n            font-family: system-ui, -apple-system, 'Segoe UI', Roboto, sans-serif;\n        }\n        body {\n            background: #f4f7fb;\n            margin: 0;\n            min-height: 100vh;\n            display: flex;\n            justify-content: center;\n            padding: 1.5rem;\n            position: relative;\n        }\n        .app-container {\n            max-width: 1400px;\n            width: 100%;\n            background: white;\n            border-radius: 2rem;\n            box-shadow: 0 20px 40px rgba(0,0,0,0.08);\n            padding: 2rem;\n        }\n        h1 {\n            font-weight: 600;\n            font-size: 1.8rem;\n            margin: 0 0 0.25rem 0;\n            color: #1e293b;\n            display: flex;\n            align-items: center;\n            gap: 0.5rem;\n            flex-wrap: wrap;\n        }\n        .subhead {\n            color: #475569;\n            margin-bottom: 2rem;\n            font-size: 1rem;\n            border-left: 4px solid #a5b4fc;\n            padding-left: 1rem;\n            background: #f8fafc;\n            border-radius: 0 1rem 1rem 0;\n            line-height: 1.5;\n        }\n        /* 控制面板 */\n        .control-panel {\n            background: #ffffffdd;\n            backdrop-filter: blur(4px);\n            border: 1px solid #e2e8f0;\n            border-radius: 1.5rem;\n            padding: 1.5rem;\n            margin-bottom: 2rem;\n            box-shadow: 0 8px 20px rgba(0,0,0,0.02);\n            display: flex;\n            flex-direction: column;\n            gap: 1.5rem;\n        }\n        .size-row {\n            display: flex;\n            flex-wrap: wrap;\n            align-items: center;\n            gap: 1rem;\n            background: #f1f4f9;\n            padding: 1rem 1.5rem;\n            border-radius: 3rem;\n        }\n        .size-row label {\n            font-weight: 600;\n            color: #1e293b;\n        }\n        .size-row input {\n            width: 100px;\n            padding: 0.6rem 1rem;\n            border: 1px solid #cbd5e1;\n            border-radius: 40px;\n            font-size: 1rem;\n            text-align: center;\n            background: white;\n        }\n        .size-row input:focus {\n            outline: none;\n            border-color: #4f46e5;\n            box-shadow: 0 0 0 3px rgba(79, 70, 229, 0.2);\n        }\n        .size-row button {\n            background: #4f46e5;\n            border: none;\n            color: white;\n            padding: 0.6rem 1.8rem;\n            border-radius: 40px;\n            font-weight: 500;\n            cursor: pointer;\n            transition: 0.15s;\n            box-shadow: 0 4px 8px rgba(79, 70, 229, 0.3);\n        }\n        .size-row button:hover {\n            background: #4338ca;\n        }\n        .info-edit-wrapper {\n            display: flex;\n            flex-wrap: wrap;\n            gap: 2rem;\n            align-items: flex-start;\n        }\n        .info-area {\n            flex: 2;\n            min-width: 280px;\n        }\n        .edit-area {\n            flex: 3;\n            min-width: 300px;\n        }\n        .selected-badge {\n            background: #e0e7ff;\n            color: #1e3a8a;\n            font-weight: 600;\n            padding: 0.4rem 1rem;\n            border-radius: 40px;\n            display: inline-block;\n            font-size: 0.9rem;\n            margin-bottom: 0.8rem;\n        }\n        .current-text-display {\n            background: #f1f5f9;\n            padding: 0.8rem 1rem;\n            border-radius: 18px;\n            font-size: 1rem;\n            margin: 0.5rem 0 1rem 0;\n            border: 1px solid #cbd5e1;\n            word-break: break-word;\n            min-height: 4rem;\n            max-height: 6rem;\n            overflow-y: auto;\n        }\n        .label {\n            font-weight: 500;\n            color: #334155;\n            margin-bottom: 0.3rem;\n            font-size: 0.9rem;\n        }\n        .row {\n            display: flex;\n            flex-wrap: wrap;\n            gap: 0.8rem;\n            align-items: center;\n            margin-top: 0.8rem;\n        }\n        textarea {\n            width: 100%;\n            padding: 0.8rem 1rem;\n            border: 1px solid #cbd5e1;\n            border-radius: 20px;\n            font-size: 0.95rem;\n            resize: vertical;\n            background: white;\n            transition: 0.15s;\n            font-family: inherit;\n        }\n        textarea:focus {\n            outline: none;\n            border-color: #818cf8;\n            box-shadow: 0 0 0 3px rgba(129, 140, 248, 0.2);\n        }\n        button {\n            background: white;\n            border: 1px solid #cbd5e1;\n            padding: 0.6rem 1.4rem;\n            border-radius: 40px;\n            font-weight: 500;\n            color: #1e293b;\n            cursor: pointer;\n            transition: 0.15s;\n            display: inline-flex;\n            align-items: center;\n            gap: 0.4rem;\n            box-shadow: 0 2px 6px rgba(0,0,0,0.02);\n        }\n        button:hover {\n            background: #f1f5f9;\n            border-color: #94a3b8;\n        }\n        button.primary {\n            background: #4f46e5;\n            border-color: #4f46e5;\n            color: white;\n        }\n        button.primary:hover {\n            background: #4338ca;\n        }\n        .file-input {\n            display: none;\n        }\n        /* 网格 — 固定10列 */\n        .grid {\n            display: grid;\n            grid-template-columns: repeat(10, minmax(110px, 1fr));\n            gap: 1rem;\n            margin-top: 1rem;\n            padding: 0.5rem 0.2rem 0.5rem 0.2rem;\n            background: #f9f9fc;\n            border-radius: 1.5rem;\n        }\n        .card {\n            background: white;\n            border-radius: 1.2rem;\n            padding: 0.8rem 0.5rem 0.5rem 0.5rem;\n            box-shadow: 0 6px 12px rgba(0,0,0,0.02);\n            transition: all 0.15s;\n            border: 2px solid transparent;\n            display: flex;\n            flex-direction: column;\n            align-items: center;\n            cursor: pointer;\n        }\n        .card.selected {\n            border-color: #4f46e5;\n            background: #f5f3ff;\n            transform: scale(1.01);\n            box-shadow: 0 12px 24px -8px rgba(79, 70, 229, 0.3);\n        }\n        .card img {\n            width: 100px;\n            height: 100px;\n            object-fit: cover;\n            border-radius: 14px;\n            background: #eef2f6;\n            box-shadow: 0 4px 8px rgba(0,0,0,0.05);\n            pointer-events: none;\n            border: 1px solid #e9eef2;\n        }\n        /* 隐藏编号 */\n        .card-index {\n            display: none;\n        }\n        .hint {\n            font-size: 0.85rem;\n            color: #6b7280;\n            margin-top: 0.5rem;\n        }\n        .footer-actions {\n            display: flex;\n            gap: 0.8rem;\n            margin-top: 1.5rem;\n            flex-wrap: wrap;\n            border-top: 1px dashed #d1d9e6;\n            padding-top: 1.5rem;\n            align-items: center;\n        }\n        /* 中央弹窗模态框 — 无序号 */\n        .modal-overlay {\n            position: fixed;\n            top: 0;\n            left: 0;\n            width: 100%;\n            height: 100%;\n            background: rgba(0,0,0,0.3);\n            display: none;\n            align-items: center;\n            justify-content: center;\n            z-index: 2000;\n        }\n        .modal-content {\n            background: white;\n            border-radius: 24px;\n            padding: 2rem;\n            max-width: 400px;\n            width: 80%;\n            box-shadow: 0 30px 50px rgba(0,0,0,0.3);\n            position: relative;\n            text-align: center;\n        }\n        .modal-content p {\n            font-size: 1.2rem;\n            color: #1e293b;\n            margin: 1rem 0;\n            word-break: break-word;\n            white-space: pre-wrap;\n        }\n        .modal-close {\n            position: absolute;\n            top: 12px;\n            right: 16px;\n            background: none;\n            border: none;\n            font-size: 1.8rem;\n            line-height: 1;\n            cursor: pointer;\n            color: #94a3b8;\n            padding: 0;\n            width: 32px;\n            height: 32px;\n            display: flex;\n            align-items: center;\n            justify-content: center;\n            border-radius: 50%;\n        }\n        .modal-close:hover {\n            background: #f1f5f9;\n            color: #475569;\n        }\n        /* 编辑模式开关样式 */\n        .edit-mode-btn {\n            background: #e0e7ff;\n            border-color: #818cf8;\n            color: #1e3a8a;\n            font-weight: 600;\n        }\n        .edit-mode-btn.active {\n            background: #4f46e5;\n            border-color: #4f46e5;\n            color: white;\n        }\n    </style>\n</head>\n<body>\n<div class=\"app-container\">\n    <h1>🖼️ 图片墙 · 编辑模式无高亮 + 固定初始图</h1>\n    <div class=\"subhead\">每个格子初始图片固定不动；文字和点击后图片绑定，可随机打乱；初始化顺序恢复原始配对。编辑模式下点击图片无高亮边框，仅编辑区更新。</div>\n\n    <!-- 控制面板 -->\n    <div class=\"control-panel\">\n        <!-- 第一行：数量控制 -->\n        <div class=\"size-row\">\n            <label>🔢 格子数量</label>\n            <input type=\"number\" id=\"sizeInput\" min=\"1\" max=\"500\" value=\"50\" step=\"1\">\n            <button id=\"resizeBtn\">调整数量</button>\n            <span style=\"color:#475569; font-size:0.9rem;\">（始终按10列排列）</span>\n        </div>\n\n        <!-- 第二行：编辑区 -->\n        <div class=\"info-edit-wrapper\">\n            <div class=\"info-area\">\n                <div class=\"selected-badge\" id=\"selectedBadge\">⚡ 当前选中: 第1项</div>\n                <div class=\"label\">📄 当前文字 (只读预览)</div>\n                <div class=\"current-text-display\" id=\"currentTextDisplay\">这是第1个选项的描述。</div>\n            </div>\n            <div class=\"edit-area\">\n                <div class=\"label\">✏️ 编辑文字 (修改后点“更新”)</div>\n                <textarea id=\"editTextInput\" rows=\"2\" placeholder=\"在这里修改当前选中项的文字...\"></textarea>\n                <div class=\"row\">\n                    <button class=\"primary\" id=\"updateTextBtn\">💾 更新当前文字</button>\n                    <button id=\"changeInitialPicBtn\">🖼️ 更换初始图片</button>\n                    <button id=\"setClickedPicBtn\">🔁 设置点击后图片</button>\n                    <input type=\"file\" id=\"fileInput\" class=\"file-input\" accept=\"image/*\">\n                </div>\n                <div class=\"hint\">• 点击图片弹出文字 • 图片变点击后图 • 可分别上传两种图片</div>\n            </div>\n        </div>\n    </div>\n\n    <!-- 网格容器 -->\n    <div class=\"grid\" id=\"gridContainer\"></div>\n\n    <!-- 底部工具条 + 编辑模式开关 -->\n    <div class=\"footer-actions\">\n        <button id=\"toggleEditModeBtn\" class=\"edit-mode-btn\">📝 编辑模式: 关</button>\n        <button id=\"shuffleBtn\">🎲 随机打乱文字+点击图</button>\n        <button id=\"initOrderBtn\">🔄 初始化顺序</button>\n        <button id=\"resetBtn\">🔁 重置内容为默认</button>\n        <span style=\"flex:1; text-align:right; font-size:0.85rem; color:#94a3b8;\" id=\"storageStatus\">📦 本地自动保存 ✓</span>\n    </div>\n</div>\n\n<!-- 中央弹窗（无序号） -->\n<div id=\"modalOverlay\" class=\"modal-overlay\">\n    <div class=\"modal-content\">\n        <button class=\"modal-close\" id=\"modalClose\">&times;</button>\n        <p id=\"modalText\">这是文字内容</p>\n    </div>\n</div>\n\n<script>\n    (function() {\n        // ---------- 配置 ----------\n        const STORAGE_KEY = 'flexibleGridData';\n        const MAX_ITEMS = 500;\n        const DEFAULT_SIZE = 50;\n\n        // DOM 元素\n        const gridEl = document.getElementById('gridContainer');\n        const selectedBadge = document.getElementById('selectedBadge');\n        const currentTextDisplay = document.getElementById('currentTextDisplay');\n        const editTextInput = document.getElementById('editTextInput');\n        const updateTextBtn = document.getElementById('updateTextBtn');\n        const changeInitialPicBtn = document.getElementById('changeInitialPicBtn');\n        const setClickedPicBtn = document.getElementById('setClickedPicBtn');\n        const fileInput = document.getElementById('fileInput');\n        const resetBtn = document.getElementById('resetBtn');\n        const shuffleBtn = document.getElementById('shuffleBtn');\n        const initOrderBtn = document.getElementById('initOrderBtn');\n        const toggleEditModeBtn = document.getElementById('toggleEditModeBtn');\n        const storageStatus = document.getElementById('storageStatus');\n        const sizeInput = document.getElementById('sizeInput');\n        const resizeBtn = document.getElementById('resizeBtn');\n\n        // 模态框元素\n        const modalOverlay = document.getElementById('modalOverlay');\n        const modalClose = document.getElementById('modalClose');\n        const modalText = document.getElementById('modalText');\n\n        // ---------- 核心数据结构 ----------\n        // grids: 每个格子固定属性 { initialImageUrl, clicked }\n        // stickers: 每个贴纸 { text, clickedImageUrl, originalIndex }，originalIndex 记录该贴纸原本所属的格子索引\n        let grids = [];\n        let stickers = [];\n        let selectedIndex = 0;          // 当前选中的格子索引\n        let uploadMode = 'initial';      // 'initial' 或 'clicked'\n        let editMode = false;            // 编辑模式：true=编辑模式（点击不触发效果，无高亮），false=正常模式\n\n        // ---------- 工具函数：默认图片 ----------\n        function createDefaultInitialImageURL(index) {\n            const hue = (index * 31) % 360;\n            const svg = `<svg xmlns=\"http://www.w3.org/2000/svg\" width=\"100\" height=\"100\" viewBox=\"0 0 100 100\">\n                <rect width=\"100\" height=\"100\" fill=\"hsl(${hue}, 70%, 60%)\" />\n                <text x=\"50\" y=\"50\" font-size=\"36\" text-anchor=\"middle\" dy=\"0.35em\" fill=\"white\" font-family=\"Arial, sans-serif\" font-weight=\"bold\">${index+1}</text>\n            </svg>`;\n            return 'data:image/svg+xml,' + encodeURIComponent(svg);\n        }\n\n        function createDefaultClickedImageURL(index) {\n            const svg = `<svg xmlns=\"http://www.w3.org/2000/svg\" width=\"100\" height=\"100\" viewBox=\"0 0 100 100\">\n                <rect width=\"100\" height=\"100\" fill=\"#9ca3af\" rx=\"12\" ry=\"12\" />\n                <circle cx=\"50\" cy=\"50\" r=\"25\" fill=\"white\" />\n                <path d=\"M38 50 L48 60 L62 40\" stroke=\"#4f46e5\" stroke-width=\"6\" fill=\"none\" stroke-linecap=\"round\" stroke-linejoin=\"round\" />\n            </svg>`;\n            return 'data:image/svg+xml,' + encodeURIComponent(svg);\n        }\n\n        // 生成默认数据\n        function generateDefaultData(count) {\n            const newGrids = [];\n            const newStickers = [];\n            for (let i = 0; i < count; i++) {\n                newGrids.push({\n                    initialImageUrl: createDefaultInitialImageURL(i),\n                    clicked: false\n                });\n                newStickers.push({\n                    text: `第 ${i+1} 号选项的描述。点击图片选中，可自由编辑。`,\n                    clickedImageUrl: createDefaultClickedImageURL(i),\n                    originalIndex: i\n                });\n            }\n            return { grids: newGrids, stickers: newStickers };\n        }\n\n        // 深拷贝\n        function deepCopyData() {\n            return {\n                grids: JSON.parse(JSON.stringify(grids)),\n                stickers: JSON.parse(JSON.stringify(stickers))\n            };\n        }\n\n        // ---------- 本地存储 ----------\n        function saveToLocalStorage() {\n            try {\n                localStorage.setItem(STORAGE_KEY, JSON.stringify({ grids, stickers }));\n                storageStatus.innerText = '📦 已自动保存到本地 ✓';\n                storageStatus.style.color = '#4f46e5';\n            } catch (e) {\n                console.warn('存储失败', e);\n                let msg = '⚠️ 保存失败';\n                if (e.name === 'QuotaExceededError') {\n                    msg = '⚠️ 本地存储空间不足，图片可能过大';\n                }\n                storageStatus.innerText = msg;\n                storageStatus.style.color = '#b91c1c';\n            }\n        }\n\n        function loadFromLocalStorage() {\n            const raw = localStorage.getItem(STORAGE_KEY);\n            if (!raw) return null;\n            try {\n                const parsed = JSON.parse(raw);\n                if (parsed && Array.isArray(parsed.grids) && Array.isArray(parsed.stickers) &&\n                    parsed.grids.length === parsed.stickers.length) {\n                    // 简单验证\n                    const valid = parsed.grids.every(g => g && typeof g.initialImageUrl === 'string') &&\n                                 parsed.stickers.every(s => s && typeof s.text === 'string' && typeof s.clickedImageUrl === 'string' && typeof s.originalIndex === 'number');\n                    if (valid) {\n                        // 确保 clicked 字段存在\n                        parsed.grids.forEach(g => g.clicked = g.clicked || false);\n                        return parsed;\n                    }\n                }\n            } catch (e) {}\n            return null;\n        }\n\n        // 初始化数据\n        function initData() {\n            const stored = loadFromLocalStorage();\n            if (stored) {\n                grids = stored.grids;\n                stickers = stored.stickers;\n                sizeInput.value = grids.length;\n            } else {\n                const defaultData = generateDefaultData(DEFAULT_SIZE);\n                grids = defaultData.grids;\n                stickers = defaultData.stickers;\n                sizeInput.value = DEFAULT_SIZE;\n            }\n            if (selectedIndex >= grids.length) selectedIndex = grids.length - 1;\n            if (selectedIndex < 0 && grids.length > 0) selectedIndex = 0;\n        }\n\n        // ---------- 高亮刷新函数（根据 editMode 和 selectedIndex 更新卡片 selected 类）----------\n        function refreshHighlight() {\n            const cards = gridEl.querySelectorAll('.card');\n            if (editMode) {\n                // 编辑模式下，移除所有高亮\n                cards.forEach(card => card.classList.remove('selected'));\n            } else {\n                // 正常模式下，给当前选中的卡片添加高亮，其余移除\n                cards.forEach((card, idx) => {\n                    if (idx === selectedIndex) {\n                        card.classList.add('selected');\n                    } else {\n                        card.classList.remove('selected');\n                    }\n                });\n            }\n        }\n\n        // ---------- 渲染网格 ----------\n        function renderGrid() {\n            gridEl.innerHTML = '';\n            for (let i = 0; i < grids.length; i++) {\n                const grid = grids[i];\n                const sticker = stickers[i]; // 当前格子显示的贴纸\n                const card = document.createElement('div');\n                card.className = 'card';\n                card.dataset.index = i;\n\n                const img = document.createElement('img');\n                // 显示逻辑：如果格子已点击，则显示当前贴纸的点击后图片，否则显示格子的初始图片\n                img.src = grid.clicked ? sticker.clickedImageUrl : grid.initialImageUrl;\n                img.alt = `选项${i+1}`;\n                img.loading = 'lazy';\n\n                card.appendChild(img);\n                gridEl.appendChild(card);\n            }\n            // 根据当前模式刷新高亮\n            refreshHighlight();\n            updateInfoPanelForIndex(selectedIndex);\n        }\n\n        // 更新单个卡片图片（根据当前状态）\n        function updateCardImage(index) {\n            const cards = gridEl.querySelectorAll('.card');\n            if (index >= 0 && index < cards.length) {\n                const img = cards[index].querySelector('img');\n                const grid = grids[index];\n                const sticker = stickers[index];\n                if (img && grid && sticker) {\n                    img.src = grid.clicked ? sticker.clickedImageUrl : grid.initialImageUrl;\n                }\n            }\n        }\n\n        // 更新信息面板\n        function updateInfoPanelForIndex(index) {\n            if (!grids.length) {\n                selectedBadge.innerText = '⚡ 没有格子';\n                currentTextDisplay.innerText = '—';\n                editTextInput.value = '';\n                return;\n            }\n            if (index < 0 || index >= grids.length) index = 0;\n            const sticker = stickers[index];\n            currentTextDisplay.innerText = sticker.text;\n            editTextInput.value = sticker.text;\n            selectedBadge.innerText = `⚡ 当前选中: 第${index+1}项 / 共${grids.length}项`;\n        }\n\n        function setSelectedIndex(index) {\n            if (!grids.length) {\n                selectedIndex = -1;\n                updateInfoPanelForIndex(-1);\n                return;\n            }\n            if (index < 0) index = 0;\n            if (index >= grids.length) index = grids.length - 1;\n            if (index === selectedIndex && index >= 0) {\n                // 相同索引也要刷新面板，但不需要刷新高亮（因为高亮可能因模式变化已正确）\n                updateInfoPanelForIndex(index);\n                return;\n            }\n\n            selectedIndex = index;\n            // 根据当前模式更新高亮\n            refreshHighlight();\n            updateInfoPanelForIndex(index);\n        }\n\n        function updateCurrentText() {\n            if (selectedIndex < 0 || !grids.length) {\n                alert('没有可编辑的格子');\n                return;\n            }\n            const newText = editTextInput.value.trim() || '(空描述)';\n            stickers[selectedIndex].text = newText;\n            currentTextDisplay.innerText = newText;\n            saveToLocalStorage();\n        }\n\n        // 调整格子数量\n        function resizeItems(newSize) {\n            newSize = Math.min(MAX_ITEMS, Math.max(1, parseInt(newSize, 10) || 1));\n            const oldLength = grids.length;\n            if (newSize === oldLength) return;\n\n            let newGrids, newStickers;\n            if (newSize > oldLength) {\n                newGrids = grids.slice();\n                newStickers = stickers.slice();\n                for (let i = oldLength; i < newSize; i++) {\n                    newGrids.push({\n                        initialImageUrl: createDefaultInitialImageURL(i),\n                        clicked: false\n                    });\n                    newStickers.push({\n                        text: `第 ${i+1} 号选项的描述。点击图片选中，可自由编辑。`,\n                        clickedImageUrl: createDefaultClickedImageURL(i),\n                        originalIndex: i\n                    });\n                }\n            } else {\n                newGrids = grids.slice(0, newSize);\n                newStickers = stickers.slice(0, newSize);\n                // 注意：截断后，超出部分的贴纸被丢弃，但它们的 originalIndex 可能大于新长度，这没关系，因为不再使用。\n            }\n\n            grids = newGrids;\n            stickers = newStickers;\n            if (selectedIndex >= newSize) selectedIndex = newSize - 1;\n            if (selectedIndex < 0 && newSize > 0) selectedIndex = 0;\n\n            renderGrid();\n            sizeInput.value = newSize;\n            saveToLocalStorage();\n        }\n\n        // ---------- 随机打乱文字+点击后图片（仅打乱 stickers 数组，保持 originalIndex 不变）----------\n        function shuffleStickers() {\n            if (stickers.length === 0) return;\n            // Fisher-Yates 打乱 stickers 数组\n            for (let i = stickers.length - 1; i > 0; i--) {\n                const j = Math.floor(Math.random() * (i + 1));\n                [stickers[i], stickers[j]] = [stickers[j], stickers[i]];\n            }\n            // 打乱后，所有格子的 clicked 状态应重置为 false，因为贴纸变了\n            grids.forEach(g => g.clicked = false);\n            // 重新渲染网格\n            renderGrid();\n            saveToLocalStorage();\n        }\n\n        // ---------- 初始化顺序：按 originalIndex 排序 stickers，恢复原始配对，并重置点击状态 ----------\n        function restoreOriginalOrder() {\n            if (stickers.length === 0) return;\n            // 按 originalIndex 升序排序 stickers\n            stickers.sort((a, b) => a.originalIndex - b.originalIndex);\n            // 重置所有格子点击状态\n            grids.forEach(g => g.clicked = false);\n            renderGrid();\n            saveToLocalStorage();\n        }\n\n        // ---------- 重置内容为默认（图片和文字都变为默认）----------\n        function resetToDefault() {\n            const count = grids.length;\n            const defaultData = generateDefaultData(count);\n            grids = defaultData.grids;\n            stickers = defaultData.stickers;\n            renderGrid();\n            setSelectedIndex(0);\n            saveToLocalStorage();\n        }\n\n        // ---------- 中央弹窗 ----------\n        function showModal(text) {\n            modalText.innerText = text;\n            modalOverlay.style.display = 'flex';\n        }\n\n        function hideModal() {\n            modalOverlay.style.display = 'none';\n        }\n\n        // ---------- 图片点击处理（正常模式下触发） ----------\n        function handleCardClick(index) {\n            if (index < 0 || index >= grids.length) return;\n            const grid = grids[index];\n            const sticker = stickers[index];\n            if (grid.clicked) return; // 已点击过，无法再次点击\n\n            // 弹出文字\n            showModal(sticker.text);\n\n            // 标记格子为已点击，并更新图片\n            grid.clicked = true;\n            updateCardImage(index);\n            saveToLocalStorage();\n        }\n\n        // ---------- 文件上传处理 ----------\n        function handleFileUpload(mode, targetIndex) {\n            const file = fileInput.files[0];\n            if (!file) return;\n            if (!file.type.startsWith('image/')) {\n                alert('请选择一个图片文件');\n                fileInput.value = '';\n                return;\n            }\n\n            const reader = new FileReader();\n            reader.onload = (loadEvent) => {\n                const dataUrl = loadEvent.target.result;\n                if (targetIndex < 0 || targetIndex >= grids.length) return;\n\n                if (mode === 'initial') {\n                    // 更换格子的初始图片\n                    grids[targetIndex].initialImageUrl = dataUrl;\n                    // 如果该格子尚未点击，则立即更新显示\n                    if (!grids[targetIndex].clicked) {\n                        updateCardImage(targetIndex);\n                    }\n                } else {\n                    // 更换当前格子贴纸的点击后图片\n                    stickers[targetIndex].clickedImageUrl = dataUrl;\n                    // 如果该格子已经点击，则立即更新显示\n                    if (grids[targetIndex].clicked) {\n                        updateCardImage(targetIndex);\n                    }\n                }\n                saveToLocalStorage();\n                fileInput.value = '';\n            };\n            reader.onerror = () => {\n                alert('读取文件失败');\n                fileInput.value = '';\n            };\n            reader.readAsDataURL(file);\n        }\n\n        // ---------- 切换编辑模式 ----------\n        function toggleEditMode() {\n            editMode = !editMode;\n            if (editMode) {\n                toggleEditModeBtn.textContent = '📝 编辑模式: 开';\n                toggleEditModeBtn.classList.add('active');\n            } else {\n                toggleEditModeBtn.textContent = '📝 编辑模式: 关';\n                toggleEditModeBtn.classList.remove('active');\n            }\n            // 刷新高亮显示\n            refreshHighlight();\n        }\n\n        // ---------- 事件绑定 ----------\n        function bindEvents() {\n            // 网格点击：先选中，然后根据编辑模式决定是否触发点击效果\n            gridEl.addEventListener('click', (e) => {\n                const card = e.target.closest('.card');\n                if (!card) return;\n                const idx = card.dataset.index;\n                if (idx !== undefined) {\n                    const index = parseInt(idx, 10);\n                    setSelectedIndex(index);\n                    // 只有非编辑模式下才执行真正的点击操作\n                    if (!editMode) {\n                        handleCardClick(index);\n                    }\n                }\n            });\n\n            // 模态框关闭\n            modalClose.addEventListener('click', hideModal);\n            modalOverlay.addEventListener('click', (e) => {\n                if (e.target === modalOverlay) hideModal();\n            });\n\n            // 更新文字\n            updateTextBtn.addEventListener('click', updateCurrentText);\n\n            // 更换初始图片\n            changeInitialPicBtn.addEventListener('click', () => {\n                if (selectedIndex < 0 || !grids.length) {\n                    alert('请先点击选中一个格子');\n                    return;\n                }\n                uploadMode = 'initial';\n                fileInput.click();\n            });\n\n            // 设置点击后图片\n            setClickedPicBtn.addEventListener('click', () => {\n                if (selectedIndex < 0 || !grids.length) {\n                    alert('请先点击选中一个格子');\n                    return;\n                }\n                uploadMode = 'clicked';\n                fileInput.click();\n            });\n\n            // 文件选择处理\n            fileInput.addEventListener('change', (e) => {\n                const targetIndex = selectedIndex;\n                handleFileUpload(uploadMode, targetIndex);\n            });\n\n            // 重置内容为默认（增加确认弹窗）\n            resetBtn.addEventListener('click', () => {\n                if (confirm('确定要重置所有内容为默认吗？此操作将丢弃您所有自定义的图片和文字。')) {\n                    resetToDefault();\n                    hideModal();\n                    storageStatus.innerText = '📦 已重置并保存';\n                }\n            });\n\n            // 随机打乱文字+点击后图片\n            shuffleBtn.addEventListener('click', () => {\n                shuffleStickers();\n                hideModal();\n            });\n\n            // 初始化顺序\n            initOrderBtn.addEventListener('click', () => {\n                restoreOriginalOrder();\n                hideModal();\n            });\n\n            // 切换编辑模式\n            toggleEditModeBtn.addEventListener('click', toggleEditMode);\n\n            // 调整数量\n            resizeBtn.addEventListener('click', () => {\n                let newSize = parseInt(sizeInput.value, 10);\n                if (isNaN(newSize) || newSize < 1) newSize = 1;\n                if (newSize > MAX_ITEMS) newSize = MAX_ITEMS;\n                sizeInput.value = newSize;\n                resizeItems(newSize);\n                hideModal();\n            });\n\n            sizeInput.addEventListener('keypress', (e) => {\n                if (e.key === 'Enter') {\n                    e.preventDefault();\n                    resizeBtn.click();\n                }\n            });\n        }\n\n        // ---------- 启动 ----------\n        function init() {\n            initData();\n            renderGrid();\n            setSelectedIndex(selectedIndex >= 0 ? selectedIndex : 0);\n            bindEvents();\n        }\n\n        init();\n    })();\n</script>\n</body>\n</html>","isHtml":true,"htmlPath":"G:\\虾虾\\网页封装PAKEPLUS\\xxsr\\第二版本\\封存","htmlFiles":[],"prefix":"","pcRepo":"PakePlus-v2.1.8","iosRepo":"PakePlus-iOS-v2.1.8","androidRepo":"PakePlus-Android-v2.1.8","more":{"windows":{"label":"","title":"picture","url":"index.html (等资源+1)","userAgent":"Mozilla/5.0 (Macintosh; Intel Mac OS X 10_15_7) AppleWebKit/537.36 (KHTML, like Gecko) Chrome/130.0.0.0 Safari/537.36","width":1024,"height":1024,"theme":null,"resizable":true,"fullscreen":false,"maximized":false,"minWidth":400,"minHeight":300,"maxWidth":1920,"maxHeight":1080,"decorations":true,"transparent":false,"titleBarStyle":"Visible","visible":true,"focus":true,"closable":true,"minimizable":true,"maximizable":true,"alwaysOnTop":false,"alwaysOnBottom":false,"center":false,"shadow":true,"skipTaskbar":false,"tabbingIdentifier":null,"parent":null,"dragDropEnabled":true,"browserExtensionsEnabled":false,"devtools":true,"contentProtected":false,"hiddenTitle":false,"incognito":false,"proxyUrl":null,"useHttpsScheme":false,"zoomHotkeysEnabled":false,"acceptFirstMouse":false,"create":false,"backgroundColor":null,"backgroundThrottling":null,"javascriptDisabled":false}},"phone":{"fullScreen":false,"safeArea":{"top":0,"bottom":0,"left":0,"right":0},"header":{"show":false,"title":"","backgroundColor":"","color":"","fontSize":16,"fontWeight":"bold","loading":false,"toolBar":false,"toolBarBackgroundColor":"","toolBarColor":"","toolBarFontSize":16,"toolBarFontWeight":"bold"},"siderMenu":{"show":false,"width":0,"backgroundColor":"","color":"","fontSize":16,"fontWeight":"bold","title":"","titleColor":"","titleFontSize":16,"titleFontWeight":"bold"},"tabBar":{"show":false,"backgroundColor":"","color":"","activeColor":"","fontSize":16,"fontWeight":"bold","tabBarItem":[]},"webview":{"userAgent":"","javaScriptEnabled":true,"domStorageEnabled":true,"allowFileAccess":true,"loadWithOverviewMode":true,"setSupportZoom":true,"clearCache":true}},"ios":{"name":"bdaddedfabaaacf","showName":"picture","version":"0.0.2","webUrl":"index.html (等资源+1)","id":"com.xiaxia.myapp.ios","icon":"./app-icon.png","desc":"Package for personal use only, please do not use for commercial purposes（打包仅限个人使用，请勿传播或商业用途）","pubBody":"Package for personal use only, please do not use for commercial purposes（打包仅限个人使用，请勿传播或商业用途）","isHtml":true,"debug":false,"safeArea":"all"},"android":{"name":"bdaddedfabaaacf","showName":"picture","version":"0.0.2","webUrl":"index.html (等资源+1)","id":"com.xiaxia.myapp.android","icon":"./app-icon.png","input":"./app-icon.png","output":"./res","rounded":true,"copyTo":"./app/src/main/res","androidResDir":"./app/src/main/res","desc":"Package for personal use only, please do not use for commercial purposes（打包仅限个人使用，请勿传播或商业用途）","pubBody":"Package for personal use only, please do not use for commercial purposes（打包仅限个人使用，请勿传播或商业用途）","isHtml":true,"debug":false,"safeArea":"all"},"desktop":{"name":"bdaddedfabaaacf","showName":"picture","version":"0.0.2","id":"com.xiaxia.myapp.desktop","desc":"打包仅限个人使用，请勿传播或商业用途，否则后果自负","webUrl":"index.html (等资源+1)","iconPath":"../app-icon.png","inputPath":"../app-icon.png","tempPath":"./processed-image.png","icnsPath":"../src-tauri/icons/icon.icns","pubBody":"打包仅限个人使用，请勿传播或商业用途，否则后果自负","isHtml":true,"single":true,"state":true,"injectJq":false,"tauriApi":false,"buildMethod":"cloud","debug":false}}